crempharm/__init__.py
crempharm/database.py
crempharm/expand_mol.py
crempharm/pgrow.py
crempharm/pharm_class.py
crempharm/scripts/__init__.py
crempharm/scripts/create_hash_db.py
crempharm/scripts/crem_db_labeling.py
crempharm/scripts/get_mols_seq.py
crempharm/scripts/smarts_features.txt
crempharm-0.3.0.dist-info/LICENSE
crempharm-0.3.0.dist-info/METADATA
crempharm-0.3.0.dist-info/WHEEL
crempharm-0.3.0.dist-info/entry_points.txt
crempharm-0.3.0.dist-info/top_level.txt
crempharm-0.3.0.dist-info/RECORD
