Metadata-Version: 2.1
Name: crempharm
Version: 0.3.0
Summary: CReM-pharm: enumeration of structures based on 3D pharmacophores by means of CReM
Home-page: https://github.com/ci-lab-cz/crem-pharm
Author: Pavel Polishchuk
Author-email: pavel_polishchuk@ukr.net
Classifier: Programming Language :: Python :: 3
Classifier: License :: OSI Approved :: GNU General Public License v3 (GPLv3)
Classifier: Operating System :: OS Independent
Classifier: Topic :: Scientific/Engineering :: Bio-Informatics
Classifier: Topic :: Scientific/Engineering :: Chemistry
Requires-Python: >=3.6
License-File: LICENSE
Requires-Dist: pmapper >=1.1.3
Provides-Extra: rdkit
Requires-Dist: rdkit >=2017.09 ; extra == 'rdkit'
